Adsorber/__init__.py
Adsorber/Adsorber/Adsorber_Program.py
Adsorber/Adsorber/Part_A_Create_non_adsorbed_VASP_files.py
Adsorber/Adsorber/Part_B_adsorb_single_species_to_cluster.py
Adsorber/Adsorber/Part_B_automated_rotation_methods.py
Adsorber/Adsorber/Part_B_get_places_to_bind_to.py
Adsorber/Adsorber/Part_B_neighbour_list.py
Adsorber/Adsorber/Part_B_storage_file.py
Adsorber/Adsorber/Part_C_Create_adsorbed_VASP_Files.py
Adsorber/Adsorber/coulomb_potential.py
Adsorber/Adsorber/import_settings_into_adsorber.py
Adsorber/Adsorber/other_methods.py
Adsorber/Adsorber/repulsive_LJ_Calculator.py
Adsorber/Subsidiary_Programs/Copy_Files_from_Folder_B_to_Folder_C.py
Adsorber/Subsidiary_Programs/Part_D_Methods.py
Adsorber/Subsidiary_Programs/Run_Adsorber_Part_D_gather_information.py
Adsorber/Subsidiary_Programs/Run_Adsorber_Tidy_Finished_Jobs.py
Adsorber/Subsidiary_Programs/Run_Adsorber_compare_systems_with_same_binding.py
Adsorber/Subsidiary_Programs/Run_Adsorber_determine_unconverged_VASP_jobs.py
Adsorber/Subsidiary_Programs/Run_Adsorber_gather_traj_files.py
Adsorber/Subsidiary_Programs/Run_Adsorber_make_vacuum.py
Adsorber/Subsidiary_Programs/Run_Adsorber_only_show_submitSL_slurm.py
Adsorber/Subsidiary_Programs/Run_Adsorber_prepare_unconverged_VASP_jobs.py
Adsorber/Subsidiary_Programs/Run_Adsorber_submitSL_slurm.py
Adsorber/Subsidiary_Programs/adsorbate_atom.py
Adsorber/Subsidiary_Programs/prepare_jobs_scripts/prepare_unconverged_VASP_jobs_from_folders.py
Adsorber/Subsidiary_Programs/prepare_jobs_scripts/prepare_unconverged_VASP_jobs_from_textfile.py
Adsorber/Subsidiary_Programs/prepare_jobs_scripts/prepare_unconverged_VASP_jobs_methods.py
Adsorber-1.10.dist-info/LICENSE
Adsorber-1.10.dist-info/METADATA
Adsorber-1.10.dist-info/WHEEL
Adsorber-1.10.dist-info/top_level.txt
Adsorber-1.10.dist-info/RECORD
