Metadata-Version: 2.1
Name: Adsorber
Version: 1.10
Summary: This program is designed to adsorb molecules to the surface of a cluster in all various ways..
Home-page: https://blogs.otago.ac.nz/annagarden/
Author: Dr. Geoffrey R. Weal and Dr. Anna L. Garden
Author-email: anna.garden@otago.ac.nz
License: GNU AFFERO GENERAL PUBLIC LICENSE
Download-URL: https://github.com/GardenGroupUO/Adsorber/archive/v1.10.tar.gz
Keywords: Adsorber,ase,university-of-otago,atomic-simulation-environment,otago-university
Platform: UNKNOWN
Classifier: Development Status :: 3 - Alpha
Classifier: Intended Audience :: Science/Research
Classifier: Natural Language :: English
Classifier: Operating System :: MacOS :: MacOS X
Classifier: Operating System :: POSIX :: Linux
Classifier: Operating System :: Unix
Classifier: Topic :: Scientific/Engineering :: Chemistry
Classifier: Topic :: Scientific/Engineering :: Physics
Classifier: Topic :: Scientific/Engineering :: Mathematics
Classifier: Topic :: Scientific/Engineering :: Artificial Intelligence
Classifier: Natural Language :: English
Classifier: License :: OSI Approved :: GNU Affero General Public License v3
Classifier: Programming Language :: Python :: 3 :: Only
Classifier: Programming Language :: Python :: 3.6
Classifier: Programming Language :: Python :: 3.7
Classifier: Programming Language :: Python :: 3.8
Classifier: Programming Language :: Python :: 3.9
License-File: LICENSE
Requires-Dist: numpy
Requires-Dist: scipy
Requires-Dist: matplotlib
Requires-Dist: ase (>=3.19.0)
Requires-Dist: openpyxl
Requires-Dist: packaging
Requires-Dist: networkx
Requires-Dist: tqdm
